{
  "publicPath": "/_nuxt/",
  "all": [
    "../server/index.spa.html",
    "../server/index.ssr.html",
    "02745a7f72fc25f7563a.js",
    "0358159b199b1ee49f4f.js",
    "1a07fbb3db29e1f6224f.js",
    "2af300db394b3994a25d.js",
    "2e808e5e4376402a2184.js",
    "452279023c9d306eaebd.js",
    "69a72b32c62c366afc56.js",
    "72540426d109771d1ad8.js",
    "823e13ba439b9fe79a12.js",
    "LICENSES",
    "b82fc61bfe7eea2a2b5b.js",
    "c854b6f919996c06acde.js",
    "d0dd44cd05627d8ab432.js",
    "e66cfe8b3ef7e8e7bcd5.js",
    "f5fe6e59c95aae3d150d.js",
    "fd93c9d75735838ee6de.js",
    "icons/icon_120.e00ww0N08g0.png",
    "icons/icon_144.e00ww0N08g0.png",
    "icons/icon_152.e00ww0N08g0.png",
    "icons/icon_192.e00ww0N08g0.png",
    "icons/icon_384.e00ww0N08g0.png",
    "icons/icon_512.e00ww0N08g0.png",
    "icons/icon_64.e00ww0N08g0.png",
    "img/1cda75b.png",
    "img/267fb99.png",
    "img/31fa1a2.png",
    "img/5b91bb6.png",
    "img/847e733.png",
    "img/933386d.png",
    "img/b94542e.png",
    "img/d545c2b.png",
    "img/fb0cb74.png",
    "manifest.585c6db7.json"
  ],
  "initial": [
    "d0dd44cd05627d8ab432.js",
    "452279023c9d306eaebd.js",
    "e66cfe8b3ef7e8e7bcd5.js",
    "c854b6f919996c06acde.js"
  ],
  "async": [
    "02745a7f72fc25f7563a.js",
    "0358159b199b1ee49f4f.js",
    "1a07fbb3db29e1f6224f.js",
    "2af300db394b3994a25d.js",
    "2e808e5e4376402a2184.js",
    "69a72b32c62c366afc56.js",
    "72540426d109771d1ad8.js",
    "823e13ba439b9fe79a12.js",
    "b82fc61bfe7eea2a2b5b.js",
    "f5fe6e59c95aae3d150d.js",
    "fd93c9d75735838ee6de.js"
  ],
  "modules": {
    "14894486": [
      16
    ],
    "15738206": [
      3
    ],
    "17751351": [
      3
    ],
    "28195752": [
      15,
      32,
      30,
      29,
      25,
      26,
      31,
      27,
      28
    ],
    "35719452": [
      15,
      32,
      30,
      29,
      25,
      26,
      31,
      27,
      28
    ],
    "44418159": [
      15,
      32,
      30,
      29,
      25,
      26,
      31,
      27,
      28
    ],
    "46963256": [
      3
    ],
    "51008974": [
      2
    ],
    "52083054": [
      3
    ],
    "62773038": [
      15,
      32,
      30,
      29,
      25,
      26,
      31,
      27,
      28
    ],
    "76045641": [
      3
    ],
    "83948402": [
      15,
      32,
      30,
      29,
      25,
      26,
      31,
      27,
      28
    ],
    "95360070": [
      3
    ],
    "2cc5ccda": [
      7
    ],
    "52bd3964": [
      15,
      32,
      30,
      29,
      25,
      26,
      31,
      27,
      28
    ],
    "2cbe6ff6": [
      15,
      32,
      30,
      29,
      25,
      26,
      31,
      27,
      28
    ],
    "89b4c1ca": [
      15,
      32,
      30,
      29,
      25,
      26,
      31,
      27,
      28
    ],
    "87f9c4fa": [
      15,
      32,
      30,
      29,
      25,
      26,
      31,
      27,
      28
    ],
    "6a59d719": [
      7
    ],
    "07616a53": [
      15,
      32,
      30,
      29,
      25,
      26,
      31,
      27,
      28
    ],
    "4da4d5c8": [
      15,
      32,
      30,
      29,
      25,
      26,
      31,
      27,
      28
    ],
    "51b61d5c": [
      15,
      32,
      30,
      29,
      25,
      26,
      31,
      27,
      28
    ],
    "217ae886": [
      7
    ],
    "a6b5ee36": [
      7
    ],
    "78e3a147": [
      15,
      32,
      30,
      29,
      25,
      26,
      31,
      27,
      28
    ],
    "5ba84933": [
      15,
      32,
      30,
      29,
      25,
      26,
      31,
      27,
      28
    ],
    "72cfdecf": [
      7
    ],
    "1253f276": [
      15,
      32,
      30,
      29,
      25,
      26,
      31,
      27,
      28
    ],
    "3dbaf01a": [
      15,
      32,
      30,
      29,
      25,
      26,
      31,
      27,
      28
    ],
    "60d57b5c": [
      15,
      32,
      30,
      29,
      25,
      26,
      31,
      27,
      28
    ],
    "920683ba": [
      15,
      32,
      30,
      29,
      25,
      26,
      31,
      27,
      28
    ],
    "2e46e293": [
      15,
      32,
      30,
      29,
      25,
      26,
      31,
      27,
      28
    ],
    "ced1be8c": [
      15,
      32,
      30,
      29,
      25,
      26,
      31,
      27,
      28
    ],
    "072f37b4": [
      15,
      32,
      30,
      29,
      25,
      26,
      31,
      27,
      28
    ],
    "0e132d03": [
      7
    ],
    "f343aff0": [
      15,
      32,
      30,
      29,
      25,
      26,
      31,
      27,
      28
    ],
    "2dc27d39": [
      15,
      32,
      30,
      29,
      25,
      26,
      31,
      27,
      28
    ],
    "0d8ec7d7": [
      15,
      32,
      30,
      29,
      25,
      26,
      31,
      27,
      28
    ],
    "5040c86b": [
      15,
      32,
      30,
      29,
      25,
      26,
      31,
      27,
      28
    ],
    "97a36e12": [
      15,
      32,
      30,
      29,
      25,
      26,
      31,
      27,
      28
    ],
    "522b0b69": [
      15,
      32,
      30,
      29,
      25,
      26,
      31,
      27,
      28
    ],
    "003d72b0": [
      15,
      32,
      30,
      29,
      25,
      26,
      31,
      27,
      28
    ],
    "1a10d17f": [
      15,
      32,
      30,
      29,
      25,
      26,
      31,
      27,
      28
    ],
    "25bda612": [
      15,
      32,
      30,
      29,
      25,
      26,
      31,
      27,
      28
    ],
    "0fa1287e": [
      15,
      32,
      30,
      29,
      25,
      26,
      31,
      27,
      28
    ],
    "5dcbba40": [
      15,
      32,
      30,
      29,
      25,
      26,
      31,
      27,
      28
    ],
    "23cec993": [
      15,
      32,
      30,
      29,
      25,
      26,
      31,
      27,
      28
    ],
    "2ec56f46": [
      15,
      32,
      30,
      29,
      25,
      26,
      31,
      27,
      28
    ],
    "fdac4110": [
      15,
      32,
      30,
      29,
      25,
      26,
      31,
      27,
      28
    ],
    "4accc84f": [
      15,
      32,
      30,
      29,
      25,
      26,
      31,
      27,
      28
    ],
    "e9b04cf6": [
      7
    ],
    "543d57a9": [
      15,
      32,
      30,
      29,
      25,
      26,
      31,
      27,
      28
    ],
    "cd6965ca": [
      15,
      32,
      30,
      29,
      25,
      26,
      31,
      27,
      28
    ],
    "e3d7211a": [
      15,
      32,
      30,
      29,
      25,
      26,
      31,
      27,
      28
    ],
    "430cd524": [
      15,
      32,
      30,
      29,
      25,
      26,
      31,
      27,
      28
    ],
    "bb46ae74": [
      15,
      32,
      30,
      29,
      25,
      26,
      31,
      27,
      28
    ],
    "d15f4c16": [
      15,
      32,
      30,
      29,
      25,
      26,
      31,
      27,
      28
    ],
    "2be444c6": [
      15,
      32,
      30,
      29,
      25,
      26,
      31,
      27,
      28
    ],
    "536046d9": [
      15,
      32,
      30,
      29,
      25,
      26,
      31,
      27,
      28
    ],
    "b7d7d71a": [
      15,
      32,
      30,
      29,
      25,
      26,
      31,
      27,
      28
    ],
    "07d4d3fc": [
      15,
      32,
      30,
      29,
      25,
      26,
      31,
      27,
      28
    ],
    "8792e92e": [
      7
    ],
    "e2a8ac44": [
      15,
      32,
      30,
      29,
      25,
      26,
      31,
      27,
      28
    ],
    "a067cf70": [
      15,
      32,
      30,
      29,
      25,
      26,
      31,
      27,
      28
    ],
    "3da5d9ba": [
      15,
      32,
      30,
      29,
      25,
      26,
      31,
      27,
      28
    ],
    "3b087d64": [
      15,
      32,
      30,
      29,
      25,
      26,
      31,
      27,
      28
    ],
    "3a25011b": [
      15,
      32,
      30,
      29,
      25,
      26,
      31,
      27,
      28
    ],
    "cf093db0": [
      15,
      32,
      30,
      29,
      25,
      26,
      31,
      27,
      28
    ],
    "0d5c6488": [
      15,
      32,
      30,
      29,
      25,
      26,
      31,
      27,
      28
    ],
    "0f00879a": [
      15,
      32,
      30,
      29,
      25,
      26,
      31,
      27,
      28
    ],
    "4bd61ede": [
      15,
      32,
      30,
      29,
      25,
      26,
      31,
      27,
      28
    ],
    "3d56d680": [
      15,
      32,
      30,
      29,
      25,
      26,
      31,
      27,
      28
    ],
    "14e8dcc6": [
      15,
      32,
      30,
      29,
      25,
      26,
      31,
      27,
      28
    ],
    "7fe7da65": [
      15,
      32,
      30,
      29,
      25,
      26,
      31,
      27,
      28
    ],
    "129158a0": [
      7
    ],
    "aedc08fc": [
      15,
      32,
      30,
      29,
      25,
      26,
      31,
      27,
      28
    ],
    "0562123a": [
      15,
      32,
      30,
      29,
      25,
      26,
      31,
      27,
      28
    ],
    "7ef4948d": [
      15,
      32,
      30,
      29,
      25,
      26,
      31,
      27,
      28
    ],
    "71a80dfc": [
      15,
      32,
      30,
      29,
      25,
      26,
      31,
      27,
      28
    ],
    "271620ca": [
      15,
      32,
      30,
      29,
      25,
      26,
      31,
      27,
      28
    ],
    "35ce224e": [
      15,
      32,
      30,
      29,
      25,
      26,
      31,
      27,
      28
    ],
    "4b53dcbb": [
      15,
      32,
      30,
      29,
      25,
      26,
      31,
      27,
      28
    ],
    "4dc11ecb": [
      15,
      32,
      30,
      29,
      25,
      26,
      31,
      27,
      28
    ],
    "6cfe345f": [
      15,
      32,
      30,
      29,
      25,
      26,
      31,
      27,
      28
    ],
    "8765341e": [
      15,
      32,
      30,
      29,
      25,
      26,
      31,
      27,
      28
    ],
    "49b2fd63": [
      7
    ],
    "bc8913a6": [
      7
    ],
    "1bdced08": [
      7
    ],
    "30bf69b1": [
      7
    ],
    "67d7cf1b": [
      7
    ],
    "9b383d72": [
      7
    ],
    "547b0e35": [
      15,
      32,
      30,
      29,
      25,
      26,
      31,
      27,
      28
    ],
    "9b24b464": [
      7
    ],
    "27b11bcc": [
      15,
      32,
      30,
      29,
      25,
      26,
      31,
      27,
      28
    ],
    "6d2a0d6e": [
      15,
      32,
      30,
      29,
      25,
      26,
      31,
      27,
      28
    ],
    "7211fa99": [
      13
    ],
    "99e61d14": [
      13
    ],
    "f68fac5c": [
      7
    ],
    "919d4444": [
      7
    ],
    "305ab99a": [
      15,
      32,
      30,
      29,
      25,
      26,
      31,
      27,
      28
    ],
    "322aacd6": [
      15,
      32,
      30,
      29,
      25,
      26,
      31,
      27,
      28
    ],
    "a296dc82": [
      15,
      32,
      30,
      29,
      25,
      26,
      31,
      27,
      28
    ],
    "47e487a1": [
      15,
      32,
      30,
      29,
      25,
      26,
      31,
      27,
      28
    ],
    "dfa25658": [
      15,
      32,
      30,
      29,
      25,
      26,
      31,
      27,
      28
    ],
    "5df5d21e": [
      15,
      32,
      30,
      29,
      25,
      26,
      31,
      27,
      28
    ],
    "6892bd45": [
      15,
      32,
      30,
      29,
      25,
      26,
      31,
      27,
      28
    ],
    "27fd9c04": [
      15,
      32,
      30,
      29,
      25,
      26,
      31,
      27,
      28
    ],
    "760a7a9e": [
      15,
      32,
      30,
      29,
      25,
      26,
      31,
      27,
      28
    ],
    "9abad746": [
      15,
      32,
      30,
      29,
      25,
      26,
      31,
      27,
      28
    ],
    "8da3245a": [
      15,
      32,
      30,
      29,
      25,
      26,
      31,
      27,
      28
    ],
    "c86609e8": [
      15,
      32,
      30,
      29,
      25,
      26,
      31,
      27,
      28
    ],
    "40fafe82": [
      15,
      32,
      30,
      29,
      25,
      26,
      31,
      27,
      28
    ],
    "53dc1741": [
      15,
      32,
      30,
      29,
      25,
      26,
      31,
      27,
      28
    ],
    "a87665ea": [
      15,
      32,
      30,
      29,
      25,
      26,
      31,
      27,
      28
    ],
    "1e018cfd": [
      15,
      32,
      30,
      29,
      25,
      26,
      31,
      27,
      28
    ],
    "4110891a": [
      15,
      32,
      30,
      29,
      25,
      26,
      31,
      27,
      28
    ],
    "5db4d0f5": [
      15,
      32,
      30,
      29,
      25,
      26,
      31,
      27,
      28
    ],
    "3cf119f6": [
      15,
      32,
      30,
      29,
      25,
      26,
      31,
      27,
      28
    ],
    "ba04bd0a": [
      15,
      32,
      30,
      29,
      25,
      26,
      31,
      27,
      28
    ],
    "04b3dc2c": [
      15,
      32,
      30,
      29,
      25,
      26,
      31,
      27,
      28
    ],
    "72037c76": [
      15,
      32,
      30,
      29,
      25,
      26,
      31,
      27,
      28
    ],
    "5e2396aa": [
      15,
      32,
      30,
      29,
      25,
      26,
      31,
      27,
      28
    ],
    "c5454116": [
      15,
      32,
      30,
      29,
      25,
      26,
      31,
      27,
      28
    ],
    "7cf18004": [
      15,
      32,
      30,
      29,
      25,
      26,
      31,
      27,
      28
    ],
    "0fecd3fa": [
      15,
      32,
      30,
      29,
      25,
      26,
      31,
      27,
      28
    ],
    "9f5af72e": [
      15,
      32,
      30,
      29,
      25,
      26,
      31,
      27,
      28
    ],
    "434dd85f": [
      15,
      32,
      30,
      29,
      25,
      26,
      31,
      27,
      28
    ],
    "a1eca438": [
      15,
      32,
      30,
      29,
      25,
      26,
      31,
      27,
      28
    ],
    "707fdc5a": [
      15,
      32,
      30,
      29,
      25,
      26,
      31,
      27,
      28
    ],
    "fdead72c": [
      15,
      32,
      30,
      29,
      25,
      26,
      31,
      27,
      28
    ],
    "1405e860": [
      15,
      32,
      30,
      29,
      25,
      26,
      31,
      27,
      28
    ],
    "03bcac54": [
      15,
      32,
      30,
      29,
      25,
      26,
      31,
      27,
      28
    ],
    "b988816c": [
      15,
      32,
      30,
      29,
      25,
      26,
      31,
      27,
      28
    ],
    "7e049ce4": [
      15,
      32,
      30,
      29,
      25,
      26,
      31,
      27,
      28
    ],
    "fb183ff8": [
      15,
      32,
      30,
      29,
      25,
      26,
      31,
      27,
      28
    ],
    "c7ed0fac": [
      15,
      32,
      30,
      29,
      25,
      26,
      31,
      27,
      28
    ],
    "6889a57a": [
      15,
      32,
      30,
      29,
      25,
      26,
      31,
      27,
      28
    ],
    "e59d488e": [
      15,
      32,
      30,
      29,
      25,
      26,
      31,
      27,
      28
    ],
    "0036d158": [
      13
    ],
    "2495736f": [
      15,
      32,
      30,
      29,
      25,
      26,
      31,
      27,
      28
    ],
    "3d591661": [
      15,
      32,
      30,
      29,
      25,
      26,
      31,
      27,
      28
    ],
    "5613a33d": [
      15,
      32,
      30,
      29,
      25,
      26,
      31,
      27,
      28
    ],
    "be31ab6a": [
      15,
      32,
      30,
      29,
      25,
      26,
      31,
      27,
      28
    ],
    "16aa255c": [
      15,
      32,
      30,
      29,
      25,
      26,
      31,
      27,
      28
    ],
    "c3b234de": [
      15,
      32,
      30,
      29,
      25,
      26,
      31,
      27,
      28
    ],
    "40ff2877": [
      15,
      32,
      30,
      29,
      25,
      26,
      31,
      27,
      28
    ],
    "4e10e8f7": [
      15,
      32,
      30,
      29,
      25,
      26,
      31,
      27,
      28
    ],
    "e736e56e": [
      7
    ],
    "fed5b672": [
      15,
      32,
      30,
      29,
      25,
      26,
      31,
      27,
      28
    ],
    "4abd1668": [
      15,
      32,
      30,
      29,
      25,
      26,
      31,
      27,
      28
    ],
    "700ee7d4": [
      15,
      32,
      30,
      29,
      25,
      26,
      31,
      27,
      28
    ],
    "1ea9162f": [
      15,
      32,
      30,
      29,
      25,
      26,
      31,
      27,
      28
    ],
    "851d86cc": [
      15,
      32,
      30,
      29,
      25,
      26,
      31,
      27,
      28
    ],
    "117db11e": [
      15,
      32,
      30,
      29,
      25,
      26,
      31,
      27,
      28
    ],
    "054fd727": [
      15,
      32,
      30,
      29,
      25,
      26,
      31,
      27,
      28
    ],
    "19707b66": [
      15,
      32,
      30,
      29,
      25,
      26,
      31,
      27,
      28
    ],
    "7f8ea582": [
      15,
      32,
      30,
      29,
      25,
      26,
      31,
      27,
      28
    ],
    "f77d5b32": [
      15,
      32,
      30,
      29,
      25,
      26,
      31,
      27,
      28
    ],
    "7ca0df28": [
      15,
      32,
      30,
      29,
      25,
      26,
      31,
      27,
      28
    ],
    "f333d724": [
      15,
      32,
      30,
      29,
      25,
      26,
      31,
      27,
      28
    ],
    "3fa48767": [
      15,
      32,
      30,
      29,
      25,
      26,
      31,
      27,
      28
    ],
    "3e8927a1": [
      15,
      32,
      30,
      29,
      25,
      26,
      31,
      27,
      28
    ],
    "1537eacc": [
      15,
      32,
      30,
      29,
      25,
      26,
      31,
      27,
      28
    ],
    "48d0b5c8": [
      15,
      32,
      30,
      29,
      25,
      26,
      31,
      27,
      28
    ],
    "f298483e": [
      15,
      32,
      30,
      29,
      25,
      26,
      31,
      27,
      28
    ],
    "79eba510": [
      15,
      32,
      30,
      29,
      25,
      26,
      31,
      27,
      28
    ],
    "7e5ee9e6": [
      13
    ],
    "6f28ec49": [
      15,
      32,
      30,
      29,
      25,
      26,
      31,
      27,
      28
    ],
    "65c73b77": [
      15,
      32,
      30,
      29,
      25,
      26,
      31,
      27,
      28
    ],
    "0c3c41d4": [
      15,
      32,
      30,
      29,
      25,
      26,
      31,
      27,
      28
    ],
    "50b2cabe": [
      7
    ],
    "11873dbe": [
      7
    ],
    "6381509e": [
      7
    ],
    "1d465249": [
      7
    ],
    "cb1b44a2": [
      7
    ],
    "3ca5aa60": [
      7
    ],
    "38ddd302": [
      7
    ],
    "bdc6c8e6": [
      7
    ],
    "7cc7c6fd": [
      7
    ],
    "5c85069c": [
      7
    ],
    "20b5eb9f": [
      7
    ],
    "0b857772": [
      7
    ],
    "d33928c2": [
      7
    ],
    "73930a84": [
      7
    ],
    "3f7b3fa0": [
      7
    ],
    "513df12a": [
      7
    ],
    "8869124c": [
      7
    ],
    "30b58e2d": [
      7
    ],
    "7c5b45b9": [
      15,
      32,
      30,
      29,
      25,
      26,
      31,
      27,
      28
    ],
    "073bd82b": [
      15,
      32,
      30,
      29,
      25,
      26,
      31,
      27,
      28
    ],
    "73f6abf2": [
      3
    ],
    "592949ba": [
      3
    ],
    "9ba9810c": [
      3
    ],
    "9e3e9414": [
      3
    ],
    "a344fd1a": [
      3
    ],
    "4fa02f92": [
      3
    ],
    "8ddf6a8c": [
      5
    ],
    "b14c2ec2": [
      3
    ],
    "54f32cd4": [
      3
    ],
    "373ad27f": [
      3
    ],
    "3f03ad5f": [
      3
    ],
    "378976b2": [
      3
    ],
    "8139259e": [
      3
    ],
    "07dbe4ac": [
      2
    ],
    "254b37de": [
      2
    ],
    "1b96fa31": [
      2
    ],
    "ba7d259c": [
      9
    ],
    "356357b4": [
      4
    ],
    "1beaea9e": [
      3
    ],
    "559c97e9": [
      3
    ],
    "74b1322e": [
      3
    ],
    "2f10bfc2": [
      3
    ],
    "2f39daf2": [
      3
    ],
    "0db7cb1e": [
      3
    ],
    "02db9820": [
      3
    ],
    "a13056f8": [
      3
    ],
    "0901db90": [
      3
    ],
    "01688690": [
      3
    ],
    "2c022b41": [
      3
    ],
    "c5e3afee": [
      3
    ],
    "6cf30c20": [
      3
    ],
    "7cb65b2c": [
      3
    ],
    "2dac9d8a": [
      3
    ],
    "5b0d74b0": [
      3
    ],
    "1c579e50": [
      3
    ],
    "0b110684": [
      3
    ],
    "29ac5482": [
      3
    ],
    "c09cb944": [
      2
    ],
    "439ebe56": [
      2
    ],
    "a6c3ab6e": [
      2
    ],
    "654a3227": [
      2
    ],
    "6a9ce469": [
      2
    ],
    "5c25cd47": [
      2
    ],
    "0a026b06": [
      2
    ],
    "77520b50": [
      2
    ],
    "ba17898a": [
      2
    ],
    "646a69b1": [
      2
    ],
    "4690e9ee": [
      2
    ],
    "130014b8": [
      2
    ],
    "8a2c6b9c": [
      2
    ],
    "12d27ffc": [
      2
    ],
    "47f5a96a": [
      9
    ],
    "0a305a70": [
      9
    ],
    "71ca9708": [
      4
    ],
    "06aee75e": [
      4
    ],
    "4b099c40": [
      10
    ],
    "3263e7aa": [
      10
    ],
    "68de9571": [
      3
    ],
    "c00d27a8": [
      3
    ],
    "6717b6c4": [
      3
    ],
    "1c65cbc0": [
      3
    ],
    "0e1f80b8": [
      3
    ],
    "6a850429": [
      3
    ],
    "4b112d70": [
      3
    ],
    "aa8777a2": [
      3
    ],
    "4401a6fc": [
      3
    ],
    "c7a6dd92": [
      3
    ],
    "fa74fee6": [
      3
    ],
    "d8923354": [
      3
    ],
    "3f41216b": [
      3
    ],
    "491e5f5d": [
      3
    ],
    "4d818f70": [
      3
    ],
    "7b1d9adf": [
      3
    ],
    "b433f438": [
      3
    ],
    "5c5a2b3a": [
      3
    ],
    "c09ee834": [
      3
    ],
    "66f03aca": [
      3
    ],
    "a5a88500": [
      3
    ],
    "886b7c60": [
      3
    ],
    "91b54390": [
      3
    ],
    "428053dc": [
      3
    ],
    "80f4689a": [
      3
    ],
    "47b4ae41": [
      3
    ],
    "18c2cb89": [
      3
    ],
    "e4637ad4": [
      8,
      33
    ],
    "35f30a9a": [
      8,
      33
    ],
    "cee3680a": [
      2
    ],
    "ae6477e6": [
      8,
      33
    ],
    "56e7ca78": [
      10
    ],
    "ac4b1770": [
      12
    ],
    "7ac65c4c": [
      4
    ],
    "b9f45d1e": [
      6
    ],
    "7a69f3d4": [
      9
    ],
    "75a52421": [
      17
    ]
  },
  "assetsMapping": {
    "02745a7f72fc25f7563a.js": "75d5a0f7",
    "0358159b199b1ee49f4f.js": "50145bdb",
    "1a07fbb3db29e1f6224f.js": "4262bc0b",
    "2af300db394b3994a25d.js": "417b3d9a",
    "2e808e5e4376402a2184.js": "4933800d",
    "452279023c9d306eaebd.js": "0859c165",
    "69a72b32c62c366afc56.js": "3cdf16e1",
    "72540426d109771d1ad8.js": "c7f036a6",
    "823e13ba439b9fe79a12.js": "62ceb3a9",
    "b82fc61bfe7eea2a2b5b.js": "1c1458b8",
    "c854b6f919996c06acde.js": "1a3ae26b",
    "d0dd44cd05627d8ab432.js": "6fca0322",
    "e66cfe8b3ef7e8e7bcd5.js": "7ea1d828",
    "f5fe6e59c95aae3d150d.js": "41708eb7",
    "fd93c9d75735838ee6de.js": "088549d2"
  }
}